LOCATE/LOCATE_functions.py
LOCATE/LOCATE_model.py
LOCATE/__init__.py
LOCATE_model-0.0.3.dist-info/LICENSE.txt
LOCATE_model-0.0.3.dist-info/METADATA
LOCATE_model-0.0.3.dist-info/WHEEL
LOCATE_model-0.0.3.dist-info/top_level.txt
LOCATE_model-0.0.3.dist-info/RECORD
