Metadata-Version: 2.1
Name: LOCATE-model
Version: 0.0.3
Summary: This code is attached to the paper "Microbiome-metabolome interactions predict host phenotype".
Author-email: Oshrit Shtossel <oshritvig@gmail.com>
License: Copyright (c) 2018 The Python Packaging Authority
Keywords: ML,metabolite,microbiome
Classifier: License :: OSI Approved :: MIT License
Classifier: Programming Language :: Python
Classifier: Programming Language :: Python :: 3
Requires-Python: >=3.7
License-File: LICENSE.txt
Requires-Dist: numpy (==1.21.6)
Requires-Dist: six (==1.16.0)
Requires-Dist: pandas (==1.3.5)
Requires-Dist: torch (==1.13.0)
Requires-Dist: pytorch-lightning (==1.8.3)
